{"METADATA": {"cd_municipio": "85103", "nm_municipio": "ENTRE-IJUÍS", "uf": "RS", "cd_tipo_eleicao": "2", "tipo_eleicao": "Ordinária", "turno": 1, "cand_names": {"95": ["VOTO BRANCO", "", "BRANCO", "", ""], "96": ["VOTO NULO", "", "NULO", "", ""], "25": ["PAULINHO", "DEM", "NÃO ELEITO", "A FORÇA DA UNIÃO PARA MUDAR", "PDT / PTB / PR / DEM / PSDB"], "15": ["MENEGHINE", "PMDB", "ELEITO", "ENTRE IJUIS NO CAMINHO CERTO", "PMDB / PP / PT"]}, "coalition_adjustments": {}}, "TOTALS": {"15": 4638, "25": 1591, "95": 160, "96": 247}}