{"METADATA": {"cd_municipio": "85430", "nm_municipio": "BOA VISTA DO BURICÁ", "uf": "RS", "cd_tipo_eleicao": "2", "tipo_eleicao": "Ordinária", "turno": 1, "cand_names": {"13": ["MOTA", "PT", "ELEITO", "ALIANÇA BOAVISTENSE", "PDT / PT / PC do B"], "96": ["VOTO NULO", "", "NULO", "", ""], "95": ["VOTO BRANCO", "", "BRANCO", "", ""], "15": ["MÁRIO PENZ", "PMDB", "NÃO ELEITO", "UNIÃO BOAVISTENSE", "PP / PTB / PMDB / PSB / PSDB"]}, "coalition_adjustments": {}}, "TOTALS": {"13": 2983, "15": 2180, "95": 30, "96": 68}}