{"METADATA": {"cd_municipio": "86215", "nm_municipio": "CRUZEIRO DO SUL", "uf": "RS", "cd_tipo_eleicao": "2", "tipo_eleicao": "Ordinária", "turno": 1, "cand_names": {"11": ["DINGOLA CESAR LEANDRO MARMITT", "PP", "ELEITO", "JUNTOS PARA RENOVAR", "PP / DEM / PSDB / PSD"], "12": ["JORGE", "PDT", "NÃO ELEITO", "PARTIDO ISOLADO", "PDT"], "95": ["VOTO BRANCO", "", "BRANCO", "", ""], "15": ["ZE IRAN", "PMDB", "NÃO ELEITO", "CRUZEIRO CRESCENDO COM VOCÊ", "PT / PTB / PMDB"], "96": ["VOTO NULO", "", "NULO", "", ""]}, "coalition_adjustments": {}}, "TOTALS": {"11": 3717, "12": 1933, "15": 3089, "95": 160, "96": 164}}