{"METADATA": {"cd_municipio": "86436", "nm_municipio": "ERVAL SECO", "uf": "RS", "cd_tipo_eleicao": "2", "tipo_eleicao": "Ordinária", "turno": 1, "cand_names": {"13": ["GILMAR LESCHEWITZ", "PT", "ELEITO", "AVANTE ERVAL SECO - UNINDO FORÇAS PARA CRESCER AINDA MAIS", "PP / PT / PTB"], "12": ["MARCOS CASTRO", "PDT", "NÃO ELEITO", "UNIÃO POR ERVAL SECO", "PDT / PMDB / PSB"], "96": ["VOTO NULO", "", "NULO", "", ""], "95": ["VOTO BRANCO", "", "BRANCO", "", ""]}, "coalition_adjustments": {}}, "TOTALS": {"12": 2117, "13": 2959, "95": 102, "96": 96}}