{"METADATA": {"cd_municipio": "86509", "nm_municipio": "CAPITÃO", "uf": "RS", "cd_tipo_eleicao": "2", "tipo_eleicao": "Ordinária", "turno": 1, "cand_names": {"12": ["CÉSAR LUIS BENEDUZI", "PDT", "ELEITO", "CONTINUAMOS COM A UNIÃO QUE FAZ CRESCER CAPITÃO", "PP / PDT"], "96": ["VOTO NULO", "", "NULO", "", ""], "95": ["VOTO BRANCO", "", "BRANCO", "", ""], "15": ["PAULINHO", "PMDB", "NÃO ELEITO", "CAPITÃO MERECE MUITO MAIS", "PT / PMDB"]}, "coalition_adjustments": {}}, "TOTALS": {"12": 1250, "15": 1214, "95": 9, "96": 33}}