{"METADATA": {"cd_municipio": "87092", "nm_municipio": "INDEPENDÊNCIA", "uf": "RS", "cd_tipo_eleicao": "2", "tipo_eleicao": "Ordinária", "turno": 1, "cand_names": {"14": ["TUTA", "PTB", "NÃO ELEITO", "FRENTE UNIDA POR INDEPENDENCIA", "PP / PDT / PT / PTB"], "96": ["VOTO NULO", "", "NULO", "", ""], "95": ["VOTO BRANCO", "", "BRANCO", "", ""], "15": ["BETO MARASCA", "PMDB", "ELEITO", "UNIAO POR INDEPENDENCIA", "PMDB / PSDB"]}, "coalition_adjustments": {}}, "TOTALS": {"14": 2439, "15": 2825, "95": 39, "96": 96}}