{"METADATA": {"cd_municipio": "87262", "nm_municipio": "NOVO BARREIRO", "uf": "RS", "cd_tipo_eleicao": "2", "tipo_eleicao": "Ordinária", "turno": 1, "cand_names": {"14": ["JACO", "PTB", "NÃO ELEITO", "JUNTOS POR UM NOVO TEMPO", "PTB / PSC / PSB / PC do B"], "96": ["VOTO NULO", "", "NULO", "", ""], "95": ["VOTO BRANCO", "", "BRANCO", "", ""], "15": ["MANINHO", "PMDB", "ELEITO", "COLIGAÇÃO UNIÃO POR NOVO BARREIRO", "PP / PDT / PT / PMDB / PPS"]}, "coalition_adjustments": {}}, "TOTALS": {"14": 1494, "15": 1801, "95": 22, "96": 118}}