{"METADATA": {"cd_municipio": "88323", "nm_municipio": "HERVEIRAS", "uf": "RS", "cd_tipo_eleicao": "2", "tipo_eleicao": "Ordinária", "turno": 1, "cand_names": {"40": ["CLÁUDIO GRASSEL", "PSB", "NÃO ELEITO", "UNIDOS PELO DESENVOLVIMENTO DE HERVEIRAS", "PMDB / PSB"], "14": ["NAZARIO KUENTZER", "PTB", "ELEITO", "RENOVAR É PRECISO", "PP / PTB / PSDB"], "96": ["VOTO NULO", "", "NULO", "", ""], "95": ["VOTO BRANCO", "", "BRANCO", "", ""]}, "coalition_adjustments": {}}, "TOTALS": {"14": 1380, "40": 1051, "95": 14, "96": 71}}