{"METADATA": {"cd_municipio": "88722", "nm_municipio": "TABAÍ", "uf": "RS", "cd_tipo_eleicao": "2", "tipo_eleicao": "Ordinária", "turno": 1, "cand_names": {"11": ["VADICO", "PP", "NÃO ELEITO", "TABAÍ ACIMA DE TUDO", "PP / DEM / PSDB / PMDB"], "95": ["VOTO BRANCO", "", "BRANCO", "", ""], "96": ["VOTO NULO", "", "NULO", "", ""], "13": ["JOAO BRANDAO", "PT", "ELEITO", "TABAI TEM SOLUÇÃO", "PT / PSB"], "14": ["ENIDIO N PEREIRA", "PTB", "NÃO ELEITO", "TABAI O POVO QUER MAIS!", "PDT / PTB"]}, "coalition_adjustments": {}}, "RESULTS": {"56_88722_1015": {"11": 98, "13": 78, "14": 25, "95": 2, "96": 7}, "56_88722_1023": {"11": 128, "13": 63, "14": 30, "95": 7, "96": 3}, "56_88722_1031": {"11": 147, "13": 129, "14": 115, "95": 7, "96": 12}, "56_88722_1040": {"11": 252, "13": 153, "14": 213, "95": 7, "96": 9}, "56_88722_1058": {"11": 190, "13": 248, "14": 205, "95": 10, "96": 14}, "56_88722_1066": {"11": 262, "13": 459, "14": 381, "95": 12, "96": 24}}}