{"METADATA": {"cd_municipio": "89354", "nm_municipio": "TRAMANDAÍ", "uf": "RS", "cd_tipo_eleicao": "2", "tipo_eleicao": "Ordinária", "turno": 1, "cand_names": {"10": ["ALINE SESSIM", "PRB", "NÃO ELEITO", "A FORÇA DA MULHER COM EXPERIÊNCIA E MAIS SAÚDE PARA TODOS", "PRB / PTB / PSL / PHS / PT do B"], "12": ["OSMANI", "PDT", "NÃO ELEITO", "FRENTE SOU MAIS TRAMANDAÍ", "PP / PDT / PSC / PR / PSB / PV / PSD / PC do B"], "15": ["EDEGAR RAPAKI", "PMDB", "ELEITO", "UNIÃO POPULAR POR TRAMANDAÍ", "PT / PMDB / PPS / PSDB"], "95": ["VOTO BRANCO", "", "BRANCO", "", ""], "96": ["VOTO NULO", "", "NULO", "", ""], "50": ["MARCELO ABREU", "PSOL", "NÃO ELEITO", "PARTIDO ISOLADO", "PSOL"]}, "coalition_adjustments": {}}, "RESULTS": {"110_89354_1015": {"10": 89, "12": 379, "15": 349, "50": 2, "95": 16, "96": 13}, "110_89354_1023": {"10": 132, "12": 697, "15": 723, "50": 5, "95": 57, "96": 31}, "110_89354_1031": {"10": 56, "12": 243, "15": 285, "50": 7, "95": 23, "96": 14}, "110_89354_1040": {"10": 344, "12": 802, "15": 822, "50": 5, "95": 65, "96": 62}, "110_89354_1058": {"10": 158, "12": 648, "15": 667, "50": 12, "95": 49, "96": 38}, "110_89354_1066": {"10": 123, "12": 689, "15": 861, "50": 15, "95": 45, "96": 49}, "110_89354_1074": {"10": 77, "12": 310, "15": 440, "50": 12, "95": 38, "96": 18}, "110_89354_1090": {"10": 170, "12": 914, "15": 940, "50": 18, "95": 71, "96": 51}, "110_89354_1104": {"10": 46, "12": 262, "15": 286, "50": 7, "95": 18, "96": 17}, "110_89354_1112": {"10": 82, "12": 302, "15": 400, "50": 2, "95": 17, "96": 12}, "110_89354_1120": {"10": 31, "12": 191, "15": 225, "50": 3, "95": 14, "96": 9}, "110_89354_1147": {"10": 288, "12": 653, "15": 609, "50": 9, "95": 50, "96": 35}, "110_89354_1155": {"10": 6, "12": 31, "15": 51, "95": 4, "96": 4}, "110_89354_1163": {"10": 159, "12": 615, "15": 596, "50": 9, "95": 40, "96": 42}, "110_89354_1171": {"10": 55, "12": 255, "15": 269, "50": 13, "95": 17, "96": 10}, "110_89354_1180": {"10": 42, "12": 211, "15": 254, "50": 3, "95": 17, "96": 13}, "110_89354_1317": {"10": 183, "12": 563, "15": 698, "50": 1, "95": 46, "96": 31}, "110_89354_1325": {"10": 98, "12": 426, "15": 405, "50": 7, "95": 37, "96": 24}, "110_89354_1341": {"10": 76, "12": 367, "15": 378, "50": 2, "95": 30, "96": 29}, "110_89354_1350": {"10": 27, "12": 163, "15": 187, "50": 6, "95": 14, "96": 8}, "110_89354_1368": {"10": 94, "12": 307, "15": 284, "50": 6, "95": 17, "96": 16}, "110_89354_1376": {"10": 84, "12": 452, "15": 554, "50": 11, "95": 37, "96": 35}, "110_89354_1384": {"10": 38, "12": 197, "15": 139, "95": 16, "96": 20}, "110_89354_1392": {"10": 89, "12": 243, "15": 325, "50": 7, "95": 29, "96": 13}, "110_89354_1406": {"10": 20, "12": 39, "15": 39, "95": 2}}}