{"METADATA": {"cand_names": {"22022": ["DAMOACI BRITO", "PL", "SUPLENTE", "PARTIDO ISOLADO", "PL"], "22222": ["LEANDRO SILVA", "PL", "ELEITO POR QP", "PARTIDO ISOLADO", "PL"], "20222": ["CLAUDENEY", "PODE", "SUPLENTE", "PARTIDO ISOLADO", "PODE"], "15111": ["RENATO DA FARMACIA", "MDB", "NÃO ELEITO", "PARTIDO ISOLADO", "MDB"], "95": ["VOTO BRANCO", "", "BRANCO", "", ""], "44": ["VOTO DE LEGENDA", "UNIÃO", "LEGENDA", "", ""], "20777": ["PROTETORA ANA LUCIA", "PODE", "SUPLENTE", "PARTIDO ISOLADO", "PODE"], "22111": ["PROFESSORA ELAINE MENDONÇA", "PL", "SUPLENTE", "PARTIDO ISOLADO", "PL"], "20": ["VOTO DE LEGENDA", "PODE", "LEGENDA", "", ""], "22333": ["LEIDIANE DO SINDICATO", "PL", "SUPLENTE", "PARTIDO ISOLADO", "PL"], "44567": ["CARLOS VAZ", "UNIÃO", "SUPLENTE", "PARTIDO ISOLADO", "UNIÃO"], "20200": ["AUDER BAIXINHO", "PODE", "ELEITO POR MÉDIA", "PARTIDO ISOLADO", "PODE"], "44000": ["MALU ENFERMEIRA", "UNIÃO", "SUPLENTE", "PARTIDO ISOLADO", "UNIÃO"], "44111": ["JOSÉ AUGUSTO", "UNIÃO", "ELEITO POR QP", "PARTIDO ISOLADO", "UNIÃO"], "15555": ["EDMAR MATEUS", "MDB", "NÃO ELEITO", "PARTIDO ISOLADO", "MDB"], "20000": ["TRIEL", "PODE", "ELEITO POR QP", "PARTIDO ISOLADO", "PODE"], "44123": ["LUCIANO PROMOÇÕES", "UNIÃO", "SUPLENTE", "PARTIDO ISOLADO", "UNIÃO"], "22888": ["ADÃO DAVID", "PL", "ELEITO POR MÉDIA", "PARTIDO ISOLADO", "PL"], "15333": ["VARLOR SANICA", "MDB", "NÃO ELEITO", "PARTIDO ISOLADO", "MDB"], "22": ["VOTO DE LEGENDA", "PL", "LEGENDA", "", ""], "22200": ["HERONIDES CARVALHO", "PL", "SUPLENTE", "PARTIDO ISOLADO", "PL"], "44777": ["CLEBER", "UNIÃO", "SUPLENTE", "PARTIDO ISOLADO", "UNIÃO"], "15777": ["DANIELY GUEDES", "MDB", "NÃO ELEITO", "PARTIDO ISOLADO", "MDB"], "22000": ["DRA. RAHISSA ROYTTMEN", "PL", "ELEITO POR QP", "PARTIDO ISOLADO", "PL"], "20678": ["JULIO BISPO", "PODE", "ELEITO POR QP", "PARTIDO ISOLADO", "PODE"], "20120": ["ANDEBURGO FRANKLIN", "PODE", "SUPLENTE", "PARTIDO ISOLADO", "PODE"], "96": ["VOTO NULO", "", "NULO", "", ""], "22555": ["VILSON FARIAS", "PL", "ELEITO POR QP", "PARTIDO ISOLADO", "PL"], "20123": ["TATIANNE ARAÚJO", "PODE", "SUPLENTE", "PARTIDO ISOLADO", "PODE"], "15": ["VOTO DE LEGENDA", "MDB", "LEGENDA", "", ""], "44444": ["UKAIOS BARBOZA", "UNIÃO", "SUPLENTE", "PARTIDO ISOLADO", "UNIÃO"], "15000": ["CRISTIANE", "MDB", "NÃO ELEITO", "PARTIDO ISOLADO", "MDB"], "15678": ["SEBASTIÃO RIBEIRO", "MDB", "NÃO ELEITO", "PARTIDO ISOLADO", "MDB"], "20111": ["GISLENE DO TELAO", "PODE", "SUPLENTE", "PARTIDO ISOLADO", "PODE"], "20333": ["ROGÉRIO FIGUEIRA", "PODE", "ELEITO POR QP", "PARTIDO ISOLADO", "PODE"], "44500": ["JHESSYCA PAULA", "UNIÃO", "SUPLENTE", "PARTIDO ISOLADO", "UNIÃO"], "15123": ["EUDINALIA FERNANDA", "MDB", "NÃO ELEITO", "PARTIDO ISOLADO", "MDB"], "22123": ["JOSÉ ÂNGELO", "PL", "SUPLENTE", "PARTIDO ISOLADO", "PL"]}, "coalition_adjustments": {}}, "TOTALS": {"20": 16, "20200": 178, "20333": 279, "20777": 49, "22": 80, "22000": 309, "22200": 125, "44111": 297, "44123": 222, "44777": 144, "15": 26, "22022": 155, "22123": 156, "44567": 19, "15111": 191, "22222": 195, "22333": 121, "22555": 271, "44": 18, "15000": 10, "15123": 21, "15333": 63, "15555": 8, "15678": 16, "15777": 9, "20000": 271, "20111": 162, "20120": 76, "20123": 86, "20222": 137, "20678": 349, "22111": 42, "22888": 167, "44000": 15, "44444": 2, "44500": 26, "95": 31, "96": 75}}