{"METADATA": {"cand_names": {"22022": ["LUCIO FERNANDES", "PL", "SUPLENTE", "PARTIDO ISOLADO", "PL"], "35123": ["MARLI BRASIL", "PMB", "NÃO ELEITO", "PARTIDO ISOLADO", "PMB"], "15111": ["SARGENTO GRIMALDO SOUSA", "MDB", "SUPLENTE", "PARTIDO ISOLADO", "MDB"], "10": ["VOTO DE LEGENDA", "REPUBLICANOS", "LEGENDA", "", ""], "55178": ["ADRIANO EXPRESSO GREMINHO", "PSD", "NÃO ELEITO", "PARTIDO ISOLADO", "PSD"], "77222": ["JACI NOBRE", "SOLIDARIEDADE", "NÃO ELEITO", "PARTIDO ISOLADO", "SOLIDARIEDADE"], "55": ["VOTO DE LEGENDA", "PSD", "LEGENDA", "", ""], "44000": ["URSO", "UNIÃO", "ELEITO POR QP", "PARTIDO ISOLADO", "UNIÃO"], "77": ["VOTO DE LEGENDA", "SOLIDARIEDADE", "LEGENDA", "", ""], "15555": ["SUB TENENTE ANTONIO", "MDB", "SUPLENTE", "PARTIDO ISOLADO", "MDB"], "45": ["VOTO DE LEGENDA", "PSDB", "LEGENDA", "", ""], "44123": ["NADIR SANTANA", "UNIÃO", "ELEITO POR MÉDIA", "PARTIDO ISOLADO", "UNIÃO"], "10777": ["WLAD MESQUITA", "REPUBLICANOS", "ELEITO POR QP", "PARTIDO ISOLADO", "REPUBLICANOS"], "13123": ["PROFESSORA HOSANA", "PT", "NÃO ELEITO", "FEDERAÇÃO", "Federação BRASIL DA ESPERANÇA - FE BRASIL(PT/PC do B/PV)"], "55123": ["ROSANGELA DO AGROEMPREGO", "PSD", "NÃO ELEITO", "PARTIDO ISOLADO", "PSD"], "22000": ["JADIEL", "PL", "SUPLENTE", "PARTIDO ISOLADO", "PL"], "96": ["VOTO NULO", "", "NULO", "", ""], "44007": ["EDUARDO LIMA", "UNIÃO", "SUPLENTE", "PARTIDO ISOLADO", "UNIÃO"], "77123": ["MANO DA SAÚDE", "SOLIDARIEDADE", "NÃO ELEITO", "PARTIDO ISOLADO", "SOLIDARIEDADE"], "77163": ["RONALDO BARBEIRO", "SOLIDARIEDADE", "NÃO ELEITO", "PARTIDO ISOLADO", "SOLIDARIEDADE"], "10111": ["PROF PAULA", "REPUBLICANOS", "SUPLENTE", "PARTIDO ISOLADO", "REPUBLICANOS"], "55111": ["FRANCISCO LOPES", "PSD", "NÃO ELEITO", "PARTIDO ISOLADO", "PSD"], "44444": ["DALTRO FIGUR", "UNIÃO", "SUPLENTE", "PARTIDO ISOLADO", "UNIÃO"], "25588": ["VALNUIR DO POSTO SENA", "PRD", "SUPLENTE", "PARTIDO ISOLADO", "PRD"], "10444": ["MARCELO DAL BERTO", "REPUBLICANOS", "SUPLENTE", "PARTIDO ISOLADO", "REPUBLICANOS"], "18007": ["FILIPE ANDRÉ", "REDE", "NÃO ELEITO", "FEDERAÇÃO", "Federação PSOL REDE(PSOL/REDE)"], "35222": ["FERNANDO AMARAL", "PMB", "NÃO ELEITO", "PARTIDO ISOLADO", "PMB"], "77100": ["MARCIA DE OLIVEIRA", "SOLIDARIEDADE", "NÃO ELEITO", "PARTIDO ISOLADO", "SOLIDARIEDADE"], "25333": ["PAULO CHEGADO", "PRD", "SUPLENTE", "PARTIDO ISOLADO", "PRD"], "44244": ["JANI SILVA", "UNIÃO", "SUPLENTE", "PARTIDO ISOLADO", "UNIÃO"], "44": ["VOTO DE LEGENDA", "UNIÃO", "LEGENDA", "", ""], "23": ["VOTO DE LEGENDA", "CIDADANIA", "LEGENDA", "", ""], "22190": ["SARGENTO ALBERTO", "PL", "SUPLENTE", "PARTIDO ISOLADO", "PL"], "77456": ["CLEIDE BABÁ", "SOLIDARIEDADE", "NÃO ELEITO", "PARTIDO ISOLADO", "SOLIDARIEDADE"], "10123": ["MARCOS AURÉLIO", "REPUBLICANOS", "SUPLENTE", "PARTIDO ISOLADO", "REPUBLICANOS"], "13013": ["JOABI JOSÉ", "PT", "NÃO ELEITO", "FEDERAÇÃO", "Federação BRASIL DA ESPERANÇA - FE BRASIL(PT/PC do B/PV)"], "25000": ["IDEIVA FOLETTO", "PRD", "SUPLENTE", "PARTIDO ISOLADO", "PRD"], "22221": ["GLAUBER FERREIRA", "PL", "SUPLENTE", "PARTIDO ISOLADO", "PL"], "55555": ["CASTANHA", "PSD", "NÃO ELEITO", "PARTIDO ISOLADO", "PSD"], "22220": ["DAL CANTON", "PL", "SUPLENTE", "PARTIDO ISOLADO", "PL"], "13555": ["ROSA MARIA", "PT", "NÃO ELEITO", "FEDERAÇÃO", "Federação BRASIL DA ESPERANÇA - FE BRASIL(PT/PC do B/PV)"], "10000": ["AIRTON CALLAI", "REPUBLICANOS", "ELEITO POR MÉDIA", "PARTIDO ISOLADO", "REPUBLICANOS"], "15163": ["PAULO NUNES", "MDB", "SUPLENTE", "PARTIDO ISOLADO", "MDB"], "18018": ["ESLEI BERTON", "REDE", "NÃO ELEITO", "FEDERAÇÃO", "Federação PSOL REDE(PSOL/REDE)"], "15777": ["CARLOS OSSUCHI", "MDB", "SUPLENTE", "PARTIDO ISOLADO", "MDB"], "15000": ["CILMARA CAMARGO", "MDB", "SUPLENTE", "PARTIDO ISOLADO", "MDB"], "18": ["VOTO DE LEGENDA", "REDE", "LEGENDA", "", ""], "15015": ["EDINA LODI", "MDB", "SUPLENTE", "PARTIDO ISOLADO", "MDB"], "15123": ["MARCIO ALBIERI", "MDB", "ELEITO POR QP", "PARTIDO ISOLADO", "MDB"], "55456": ["EZEQUIAS VASCONCELOS", "PSD", "NÃO ELEITO", "PARTIDO ISOLADO", "PSD"], "20444": ["DANIELA DE MORAIS", "PODE", "NÃO ELEITO", "PARTIDO ISOLADO", "PODE"], "15321": ["CHEILA DO CHOPP", "MDB", "SUPLENTE", "PARTIDO ISOLADO", "MDB"], "25190": ["TANINHA", "PRD", "SUPLENTE", "PARTIDO ISOLADO", "PRD"], "22024": ["IVANIA", "PL", "SUPLENTE", "PARTIDO ISOLADO", "PL"], "10400": ["AMÁLIA CRUZ", "REPUBLICANOS", "SUPLENTE", "PARTIDO ISOLADO", "REPUBLICANOS"], "25123": ["JACKSON LOPES", "PRD", "ELEITO POR QP", "PARTIDO ISOLADO", "PRD"], "77333": ["PROFESSOR ENOQUE REIS", "SOLIDARIEDADE", "NÃO ELEITO", "PARTIDO ISOLADO", "SOLIDARIEDADE"], "95": ["VOTO BRANCO", "", "BRANCO", "", ""], "25007": ["DÉBORA CARNEIRO", "PRD", "ELEITO POR MÉDIA", "PARTIDO ISOLADO", "PRD"], "20": ["VOTO DE LEGENDA", "PODE", "LEGENDA", "", ""], "55999": ["JULIAMA", "PSD", "NÃO ELEITO", "PARTIDO ISOLADO", "PSD"], "20200": ["ENFERMEIRA ELISANGELA TOMELERO", "PODE", "NÃO ELEITO", "PARTIDO ISOLADO", "PODE"], "18888": ["ALÊ DO POSTINHO", "REDE", "NÃO ELEITO", "FEDERAÇÃO", "Federação PSOL REDE(PSOL/REDE)"], "22777": ["KEKEU", "PL", "SUPLENTE", "PARTIDO ISOLADO", "PL"], "55035": ["FRANCISCA SILVA TIA DA MERENDA", "PSD", "NÃO ELEITO", "PARTIDO ISOLADO", "PSD"], "22": ["VOTO DE LEGENDA", "PL", "LEGENDA", "", ""], "20555": ["VALÉRIA FARIAS", "PODE", "NÃO ELEITO", "PARTIDO ISOLADO", "PODE"], "23015": ["GLAIDES", "CIDADANIA", "NÃO ELEITO", "FEDERAÇÃO", "Federação PSDB CIDADANIA(PSDB/CIDADANIA)"], "18000": ["THEXUGA", "REDE", "NÃO ELEITO", "FEDERAÇÃO", "Federação PSOL REDE(PSOL/REDE)"], "45555": ["LUAN", "PSDB", "NÃO ELEITO", "FEDERAÇÃO", "Federação PSDB CIDADANIA(PSDB/CIDADANIA)"], "35": ["VOTO DE LEGENDA", "PMB", "LEGENDA", "", ""], "44888": ["CABRAL", "UNIÃO", "SUPLENTE", "PARTIDO ISOLADO", "UNIÃO"], "18345": ["PROF JUNIOR GOMES", "REDE", "NÃO ELEITO", "FEDERAÇÃO", "Federação PSOL REDE(PSOL/REDE)"], "15678": ["TIERHIS HENRIQUE", "MDB", "SUPLENTE", "PARTIDO ISOLADO", "MDB"], "55000": ["LUCI CARVALHO", "PSD", "NÃO ELEITO", "PARTIDO ISOLADO", "PSD"], "20333": ["SUZANA CANDIDO", "PODE", "NÃO ELEITO", "PARTIDO ISOLADO", "PODE"], "50": ["VOTO DE LEGENDA", "PSOL", "LEGENDA", "", ""], "10888": ["GENIVALDO SANTOS", "REPUBLICANOS", "SUPLENTE", "PARTIDO ISOLADO", "REPUBLICANOS"], "22123": ["VANDERLEI DA PRAINHA", "PL", "SUPLENTE", "PARTIDO ISOLADO", "PL"], "20020": ["ALCEMIR PAIXÃO", "PODE", "NÃO ELEITO", "PARTIDO ISOLADO", "PODE"], "22222": ["PROFE LILIAN", "PL", "SUPLENTE", "PARTIDO ISOLADO", "PL"], "10222": ["JOAO CLEBERSON", "REPUBLICANOS", "SUPLENTE", "PARTIDO ISOLADO", "REPUBLICANOS"], "13000": ["RICARDO ANZIL", "PT", "NÃO ELEITO", "FEDERAÇÃO", "Federação BRASIL DA ESPERANÇA - FE BRASIL(PT/PC do B/PV)"], "15144": ["EDUARDO CRUZ", "MDB", "SUPLENTE", "PARTIDO ISOLADO", "MDB"], "43": ["VOTO DE LEGENDA", "PV", "LEGENDA", "", ""], "77777": ["ADEMIR SANTANA", "SOLIDARIEDADE", "NÃO ELEITO", "PARTIDO ISOLADO", "SOLIDARIEDADE"], "77000": ["FLAVIO CAMINHONEIRO", "SOLIDARIEDADE", "NÃO ELEITO", "PARTIDO ISOLADO", "SOLIDARIEDADE"], "35444": ["IRMÃO BATISTA", "PMB", "NÃO ELEITO", "PARTIDO ISOLADO", "PMB"], "13456": ["PROFESSOR ADRIANO PLÁCIDO", "PT", "NÃO ELEITO", "FEDERAÇÃO", "Federação BRASIL DA ESPERANÇA - FE BRASIL(PT/PC do B/PV)"], "44567": ["JAILTON MOTORISTA", "UNIÃO", "SUPLENTE", "PARTIDO ISOLADO", "UNIÃO"], "25012": ["JAMIR PELICIONI GRINGO", "PRD", "SUPLENTE", "PARTIDO ISOLADO", "PRD"], "10500": ["DR NELSINHO", "REPUBLICANOS", "ELEITO POR QP", "PARTIDO ISOLADO", "REPUBLICANOS"], "44044": ["TANIA JORRA", "UNIÃO", "SUPLENTE", "PARTIDO ISOLADO", "UNIÃO"], "20000": ["KASSIANO SOUZA DA TV", "PODE", "NÃO ELEITO", "PARTIDO ISOLADO", "PODE"], "10555": ["GESSICA GA MODAS", "REPUBLICANOS", "SUPLENTE", "PARTIDO ISOLADO", "REPUBLICANOS"], "13": ["VOTO DE LEGENDA", "PT", "LEGENDA", "", ""], "22122": ["HELIO DA BOYS EXPRESS", "PL", "ELEITO POR MÉDIA", "PARTIDO ISOLADO", "PL"], "25234": ["MARI DA GUARDA", "PRD", "SUPLENTE", "PARTIDO ISOLADO", "PRD"], "25": ["VOTO DE LEGENDA", "PRD", "LEGENDA", "", ""], "20002": ["DIEGO MARONESI", "PODE", "NÃO ELEITO", "PARTIDO ISOLADO", "PODE"], "20123": ["NEGUINHO", "PODE", "NÃO ELEITO", "PARTIDO ISOLADO", "PODE"], "13100": ["OBREIRA ODETE", "PT", "NÃO ELEITO", "FEDERAÇÃO", "Federação BRASIL DA ESPERANÇA - FE BRASIL(PT/PC do B/PV)"], "15": ["VOTO DE LEGENDA", "MDB", "LEGENDA", "", ""], "44555": ["CLÉO ARRUDA", "UNIÃO", "SUPLENTE", "PARTIDO ISOLADO", "UNIÃO"], "44333": ["JOSIAS CABELEIREIRO", "UNIÃO", "SUPLENTE", "PARTIDO ISOLADO", "UNIÃO"], "25153": ["DUTRA DA GUARDA", "PRD", "SUPLENTE", "PARTIDO ISOLADO", "PRD"], "18123": ["SOL MATTOSO", "REDE", "NÃO ELEITO", "FEDERAÇÃO", "Federação PSOL REDE(PSOL/REDE)"]}, "coalition_adjustments": {}}, "TOTALS": {"10": 370, "10000": 1357, "10111": 225, "10123": 446, "10222": 662, "10400": 45, "10444": 276, "10500": 2106, "10555": 88, "10777": 2564, "10888": 283, "13": 43, "13000": 137, "13013": 85, "13123": 285, "13456": 150, "13555": 127, "15000": 280, "15015": 397, "15111": 671, "15123": 1241, "15144": 383, "15163": 690, "15321": 268, "15555": 552, "15678": 623, "15777": 373, "18000": 126, "18007": 20, "18123": 43, "18888": 143, "20": 36, "20000": 1425, "20002": 84, "20020": 55, "20123": 21, "20200": 430, "20333": 89, "20444": 63, "20555": 239, "22": 224, "22000": 307, "22022": 145, "22024": 140, "22122": 1262, "22190": 383, "22220": 40, "22221": 59, "22222": 332, "22777": 117, "23015": 37, "25000": 575, "25007": 1107, "25012": 213, "25123": 1692, "25190": 203, "25234": 92, "25333": 171, "25588": 466, "35222": 84, "35444": 71, "44": 44, "44000": 1022, "44007": 191, "44044": 167, "44123": 747, "44244": 129, "44333": 679, "44444": 356, "44567": 167, "44888": 134, "50": 20, "55000": 213, "55035": 37, "55111": 489, "55123": 401, "55178": 105, "55456": 631, "55555": 57, "55999": 180, "77123": 1146, "77163": 17, "77222": 36, "77333": 373, "77456": 43, "77777": 75, "95": 1567, "96": 795, "15": 64, "55": 25, "13100": 29, "18345": 37, "22123": 196, "35123": 15, "45555": 55, "77100": 24, "23": 14, "25": 48, "43": 2, "44555": 108, "77": 32, "77000": 26, "25153": 46, "18": 9, "18018": 10, "45": 14, "35": 6}}